BlueStacksAgent/__init__.py
BlueStacksAgent/agent.py
BlueStacksAgent/actuators/__init__.py
BlueStacksAgent/actuators/adb_actuator.py
BlueStacksAgent/actuators/base.py
BlueStacksAgent/agents/__init__.py
BlueStacksAgent/agents/base.py
BlueStacksAgent/agents/mediaprojection_agent.py
BlueStacksAgent/agents/minicap_agent.py
BlueStacksAgent/agents/scrcpy_agent.py
bluestacksagent-0.2.3.dist-info/LICENSE
bluestacksagent-0.2.3.dist-info/METADATA
bluestacksagent-0.2.3.dist-info/WHEEL
bluestacksagent-0.2.3.dist-info/top_level.txt
bluestacksagent-0.2.3.dist-info/RECORD
