Metadata-Version: 2.2
Name: BlueStacksAgent
Version: 0.2.3
Summary: A Python library for real-time interaction with BlueStacks using scrcpy, minicap, and MediaProjection.
Home-page: https://github.com/AlessandroFlati/BlueStacksAgent
Author: Alessandro Flati
Author-email: alessandro.flati@gmail.com
License: MIT License
Requires-Python: <3.11,>=3.7
License-File: LICENSE
Requires-Dist: scrcpy-client
Requires-Dist: numpy
Dynamic: author
Dynamic: author-email
Dynamic: home-page
